_kSpider_internal.cpython-39-x86_64-linux-gnu.so
kSpider2.libs/libgomp-a34b3233.so.1.0.0
kSpider2.libs/libbz2-a273e504.so.1.0.6
kSpider2.libs/libz-745e0a09.so.1.2.7
kSpider2-2.0.1.dist-info/METADATA
kSpider2-2.0.1.dist-info/RECORD
kSpider2-2.0.1.dist-info/top_level.txt
kSpider2-2.0.1.dist-info/WHEEL
kSpider2-2.0.1.dist-info/entry_points.txt
kSpider2/ks_pairwise.py
kSpider2/__init__.py
kSpider2/kSpider_main.py
kSpider2/click_context.py
internal/__init__.py
internal/kSpider_internal.py
