Metadata-Version: 2.1
Name: kSpider2
Version: 2.0.1
Summary: kSpider Python interface
Home-page: UNKNOWN
License: BSD 3-Clause
Project-URL: Bug Reports, https://github.com/mr-eyes/kSpider2/issues
Project-URL: Source, https://github.com/mr-eyes/kSpider2/issues
Platform: UNKNOWN
Classifier: License :: OSI Approved :: Apache Software License
Classifier: Development Status :: 3 - Alpha
Classifier: Operating System :: POSIX :: Linux
Classifier: Programming Language :: Python
Classifier: Programming Language :: Python :: 3
Classifier: Programming Language :: Python :: 3.6
Classifier: Programming Language :: Python :: 3.7
Classifier: Programming Language :: Python :: 3.8
Classifier: Programming Language :: Python :: 3.9
Requires-Python: >=3.6
Requires-Dist: Click
